bruggeman/__about__.py
bruggeman/__init__.py
bruggeman/edelman.py
bruggeman/flow1d.py
bruggeman/flow2d.py
bruggeman/general.py
bruggeman/py.typed
bruggeman-0.1.0.dist-info/METADATA
bruggeman-0.1.0.dist-info/WHEEL
bruggeman-0.1.0.dist-info/entry_points.txt
bruggeman-0.1.0.dist-info/licenses/LICENSE
bruggeman-0.1.0.dist-info/RECORD
