Metadata-Version: 2.4
Name: bruggeman
Version: 0.1.0
Summary: Repository for the Bruggeman equations from Analytical Solutions of Geohydrological Problems (1999)
Author-email: Davíd Brakenhoff <d.brakenhoff@artesia-water.nl>
License-File: LICENSE
Requires-Python: >=3.12
Requires-Dist: mpmath
Requires-Dist: numpy
Requires-Dist: scipy
Provides-Extra: ci
Requires-Dist: mypy; extra == 'ci'
Requires-Dist: nbconvert; extra == 'ci'
Requires-Dist: nbformat; extra == 'ci'
Requires-Dist: pytest; extra == 'ci'
Requires-Dist: pytest-cov; extra == 'ci'
Requires-Dist: ruff; extra == 'ci'
Provides-Extra: dev
Requires-Dist: ipykernel; extra == 'dev'
Requires-Dist: ipython; extra == 'dev'
Requires-Dist: latexify-py; extra == 'dev'
Requires-Dist: matplotlib; extra == 'dev'
Requires-Dist: mypy; extra == 'dev'
Requires-Dist: myst-nb; extra == 'dev'
Requires-Dist: nbconvert; extra == 'dev'
Requires-Dist: nbformat; extra == 'dev'
Requires-Dist: numpydoc; extra == 'dev'
Requires-Dist: pydata-sphinx-theme; extra == 'dev'
Requires-Dist: pytest; extra == 'dev'
Requires-Dist: pytest-cov; extra == 'dev'
Requires-Dist: ruff; extra == 'dev'
Requires-Dist: sphinx; extra == 'dev'
Requires-Dist: sphinx-design; extra == 'dev'
Requires-Dist: sphinxcontrib-bibtex; extra == 'dev'
Requires-Dist: ttim; extra == 'dev'
Provides-Extra: docs
Requires-Dist: ipykernel; extra == 'docs'
Requires-Dist: ipython; extra == 'docs'
Requires-Dist: latexify-py; extra == 'docs'
Requires-Dist: matplotlib; extra == 'docs'
Requires-Dist: myst-nb; extra == 'docs'
Requires-Dist: numpydoc; extra == 'docs'
Requires-Dist: pydata-sphinx-theme; extra == 'docs'
Requires-Dist: sphinx; extra == 'docs'
Requires-Dist: sphinx-design; extra == 'docs'
Requires-Dist: sphinxcontrib-bibtex; extra == 'docs'
Requires-Dist: ttim; extra == 'docs'
Provides-Extra: latexify
Requires-Dist: latexify-py; extra == 'latexify'
